pinsy/__init__.py
pinsy/_others.py
pinsy/_pinsy.py
pinsy/cli.py
pinsy/utils.py
pinsy-0.2.4.dist-info/LICENSE
pinsy-0.2.4.dist-info/METADATA
pinsy-0.2.4.dist-info/WHEEL
pinsy-0.2.4.dist-info/entry_points.txt
pinsy-0.2.4.dist-info/top_level.txt
pinsy-0.2.4.dist-info/RECORD
