Metadata-Version: 2.1
Name: pinsy
Version: 0.2.4
Summary: A Python package to help speed up the workflow of creating beautiful CLI apps.
Home-page: https://github.com/Anas-Shakeel/pinsy
Author: Anas Shakeel
License: MIT
Keywords: python,cli,command-line,terminal,text formatting,color output,CLI app development,CLI tools,terminal UI,beautiful CLI apps,text styling
Classifier: Development Status :: 4 - Beta
Classifier: Intended Audience :: Developers
Classifier: License :: OSI Approved :: MIT License
Classifier: Operating System :: Microsoft :: Windows
Classifier: Operating System :: POSIX :: Linux
Classifier: Operating System :: MacOS
Classifier: Programming Language :: Python :: 3
Classifier: Programming Language :: Python :: 3 :: Only
Classifier: Programming Language :: Python :: 3.9
Classifier: Programming Language :: Python :: 3.10
Classifier: Programming Language :: Python :: 3.11
Classifier: Programming Language :: Python :: 3.12
Classifier: Programming Language :: Python :: 3.13
Classifier: Programming Language :: Python :: Implementation :: CPython
Classifier: Topic :: Software Development
Classifier: Topic :: Software Development :: User Interfaces
Requires-Python: >=3.9
License-File: LICENSE
Requires-Dist: colorama
Requires-Dist: cursor
Requires-Dist: ansy
Requires-Dist: readchar
